docufix/__init__.py
docufix/__main__.py
docufix/_compat.py
docufix/cli.py
docufix/core.py
docufix/rules/__init__.py
docufix/rules/ensure_final_newline.py
docufix/rules/insert_whitespace_between_cn_and_en_char.py
docufix/rules/replace_tab_with_space.py
docufix/rules/trim_trailing_blank_lines.py
docufix/rules/trim_trailing_whitespace.py
docufix/rules/unify_newline.py
docufix/utils/__init__.py
docufix/utils/colorful.py
docufix/utils/newline.py
docufix-0.3.2.dist-info/entry_points.txt
docufix-0.3.2.dist-info/LICENSE
docufix-0.3.2.dist-info/WHEEL
docufix-0.3.2.dist-info/METADATA
docufix-0.3.2.dist-info/RECORD
