Metadata-Version: 2.1
Name: docufix
Version: 0.3.2
Summary: 
Author: Nyakku Shigure
Author-email: sigure.qaq@gmail.com
Requires-Python: >=3.9,<4.0
Classifier: Programming Language :: Python :: 3
Classifier: Programming Language :: Python :: 3.9
Classifier: Programming Language :: Python :: 3.10
Requires-Dist: typing-extensions (>=4.3.0,<5.0.0); python_version < "3.11"
